setup.py
bi_get.egg-info/PKG-INFO
bi_get.egg-info/SOURCES.txt
bi_get.egg-info/dependency_links.txt
bi_get.egg-info/requires.txt
bi_get.egg-info/top_level.txt
biliget/__init__.py
biliget/video.py
biliget/vtools/__init__.py
biliget/vtools/downloader.py
biliget/vtools/headers.py
biliget/vtools/utils.py
error/__init__.py
error/cc_exception.py
error/warn.py
utils/__init__.py
utils/cc_tool.py
utils/pyffmpeg.py
utils/pypyth.py